hidimstat/__init__.py
hidimstat/_version.py
hidimstat/base_perturbation.py
hidimstat/base_variable_importance.py
hidimstat/conditional_feature_importance.py
hidimstat/desparsified_lasso.py
hidimstat/distilled_conditional_randomization_test.py
hidimstat/ensemble_clustered_inference.py
hidimstat/knockoffs.py
hidimstat/leave_one_covariate_out.py
hidimstat/permutation_feature_importance.py
hidimstat/_utils/__init__.py
hidimstat/_utils/docstring.py
hidimstat/_utils/exception.py
hidimstat/_utils/regression.py
hidimstat/_utils/scenario.py
hidimstat/_utils/utils.py
hidimstat/samplers/__init__.py
hidimstat/samplers/conditional_sampling.py
hidimstat/samplers/gaussian_knockoffs.py
hidimstat/statistical_tools/__init__.py
hidimstat/statistical_tools/aggregation.py
hidimstat/statistical_tools/multiple_testing.py
hidimstat/statistical_tools/nadeau_bengio_ttest.py
hidimstat/statistical_tools/p_values.py
hidimstat/visualization/__init__.py
hidimstat/visualization/partial_dependence_plot.py
hidimstat-0.3.0.dist-info/licenses/LICENSE
hidimstat-0.3.0.dist-info/METADATA
hidimstat-0.3.0.dist-info/WHEEL
hidimstat-0.3.0.dist-info/top_level.txt
hidimstat-0.3.0.dist-info/RECORD
