Metadata-Version: 2.4
Name: HiDimStat
Version: 0.3.0
Summary: High-dimensional statistical inference tools for Python
Author: HiDimStat developers
Maintainer-email: Bertrand Thirion <bertrand.thirion@inria.fr>
Project-URL: Repository, https://github.com/mind-inria/hidimstat
Project-URL: Documentation, https://github.com/hidimstat/hidimstat.github.io
Project-URL: Teams, https://team.inria.fr/mind/
Project-URL: Issues, https://github.com/mind-inria/hidimstat/issues
Project-URL: Discussion, https://github.com/mind-inria/hidimstat/discussions
Keywords: statistic,high dimension,variable importance
Classifier: Intended Audience :: Science/Research
Classifier: Intended Audience :: Developers
Classifier: Operating System :: Microsoft :: Windows
Classifier: Operating System :: Unix
Classifier: Operating System :: MacOS
Classifier: Operating System :: OS Independent
Classifier: Programming Language :: Python :: 3.9
Classifier: Programming Language :: Python :: 3.10
Classifier: Programming Language :: Python :: 3.11
Classifier: Programming Language :: Python :: 3.12
Classifier: Programming Language :: Python :: 3.13
Classifier: Topic :: Software Development
Classifier: Topic :: Scientific/Engineering
Requires-Python: <4,>=3.10
License-File: LICENSE
Requires-Dist: joblib<2,>=1.2.0
Requires-Dist: numpy<3,>=1.25
Requires-Dist: pandas<3,>=2.2
Requires-Dist: scikit-learn<1.9,>=1.5
Requires-Dist: scipy<2,>=1.9.2
Requires-Dist: tqdm<5,>=4.1.0
Provides-Extra: doc
Requires-Dist: matplotlib<4,>=3.8.0; extra == "doc"
Requires-Dist: nilearn<1,>=0.11.0; extra == "doc"
Requires-Dist: memory_profiler; extra == "doc"
Requires-Dist: numpydoc<2,>=1.0.0; extra == "doc"
Requires-Dist: pydata_sphinx_theme<1,>=0.15.1; extra == "doc"
Requires-Dist: seaborn<1,>=0.13; extra == "doc"
Requires-Dist: sphinxcontrib-bibtex<3,>=2.5.0; extra == "doc"
Requires-Dist: sphinx<9,>=7.0.0; extra == "doc"
Requires-Dist: sphinx-gallery<1,>=0.17.0; extra == "doc"
Requires-Dist: sphinx-prompt<2,>=1.8.0; extra == "doc"
Requires-Dist: tqdm<5,>=4.1.0; extra == "doc"
Requires-Dist: sphinx-copybutton; extra == "doc"
Provides-Extra: example
Requires-Dist: matplotlib<4,>=3.1.0; extra == "example"
Requires-Dist: seaborn<1,>=0.9; extra == "example"
Provides-Extra: style
Requires-Dist: black>=24.4.2; extra == "style"
Requires-Dist: codespell>=2.4.0; extra == "style"
Requires-Dist: isort>=5.13.2; extra == "style"
Provides-Extra: test
Requires-Dist: coverage<8,>=6.0; extra == "test"
Requires-Dist: iniconfig<3,>=0.1; extra == "test"
Requires-Dist: matplotlib<4,>=3.8.0; extra == "test"
Requires-Dist: packaging<100,>=14.0; extra == "test"
Requires-Dist: pytest<10,>=8.0; extra == "test"
Requires-Dist: pytest-cov<8,>=5.0; extra == "test"
Requires-Dist: pytest-durations<2,>=1.0.0; extra == "test"
Requires-Dist: pytest-env<2,>=1.0.0; extra == "test"
Requires-Dist: pytest-html<5,>=4.0.0; extra == "test"
Requires-Dist: pytest-mpl<1,>=0.14; extra == "test"
Requires-Dist: pytest-randomly<5,>=3.3.0; extra == "test"
Requires-Dist: pytest-reportlog<2,>=0.2.1; extra == "test"
Requires-Dist: pytest-timeout<3,>=2.3.1; extra == "test"
Requires-Dist: pytest-xdist[psutil]<4,>=3.4.0; extra == "test"
Requires-Dist: seaborn<1,>=0.12; extra == "test"
Dynamic: license-file
